Workbook

Sheet Base Tratada
A1: PORSCHE — BASE DE VENDAS TRATADA (100 registros)
A2: Tratada a partir da planilha oficial do desafio (aba Sanitized). Sem dados pessoais. Detalhes nas abas Dicionário e Tratamento.
A4: ID da venda | B4: Data da venda | C4: Data válida? | D4: Modelo | E4: Família | F4: Combustível | G4: Ano-modelo | H4: Preço (US$) | I4: Quilometragem (mi) | J4: Método de pagamento | K4: Cidade | L4: UF | M4: Região | N4: Status da entrega | O4: Grupo do status
A5: 6 | C5: Não | D5: 718 Cayman | E5: 718 | F5: Combustão | G5: 2022 | H5: 79500 | I5: 9800 | J5: Cartão de crédito | K5: Boston | L5: MA | M5: Nordeste | N5: Entregue | O5: Entregue
A6: 7 | B6: 2024-03-14 | C6: Sim | D6: 911 Turbo S | E6: 911 | F6: Combustão | G6: 2024 | H6: 235000 | I6: 1200 | J6: Transferência (wire) | K6: Seattle | L6: WA | M6: Oeste | N6: Entregue | O6: Entregue
A7: 8 | B7: 2024-04-18 | C7: Sim | D7: Cayenne Coupe | E7: Cayenne | F7: Combustão | G7: 2023 | H7: 112750 | I7: 6400 | J7: Financiamento | K7: Austin | L7: TX | M7: Sul | N7: Em trânsito | O7: Em trânsito
A8: 9 | C8: Não | D8: Macan S | E8: Macan | F8: Combustão | G8: 2021 | H8: 68900 | I8: 28 | J8: Dinheiro | K8: Denver | L8: CO | M8: Oeste | N8: Pendente | O8: Pendente
A9: 10 | B9: 2024-05-22 | C9: Sim | D9: Taycan 4S | E9: Taycan | F9: Elétrico | G9: 2024 | H9: 121000 | I9: 0 | J9: Transferência bancária | K9: Los Angeles | L9: CA | M9: Oeste | N9: Entregue | O9: Entregue
A10: 11 | B10: 2024-08-06 | C10: Sim | D10: Panamera 4 | E10: Panamera | F10: Combustão | G10: 2023 | H10: 104500 | I10: 14500 | J10: Cartão de crédito | K10: Miami | L10: FL | M10: Sul | N10: Cancelado | O10: Cancelado
A11: 12 | B11: 2024-07-11 | C11: Sim | D11: 911 Carrera S | E11: 911 | F11: Combustão | G11: 2020 | H11: 96300 | I11: 41000 | J11: Locação (leasing) | K11: New York | L11: NY | M11: Nordeste | N11: Entregue | O11: Entregue
A12: 13 | C12: Não | D12: Cayenne E-Hybrid | E12: Cayenne | F12: Híbrido | G12: 2022 | H12: 89750 | I12: 11744 | J12: Transferência (wire) | K12: San Diego | L12: CA | M12: Oeste | N12: Aguardando aprovação | O12: Pendente
A13: 14 | B13: 2024-08-19 | C13: Sim | D13: 718 Boxster | E13: 718 | F13: Combustão | G13: 2021 | H13: 73500 | I13: 22300 | J13: Cartão de débito | K13: Chicago | L13: IL | M13: Centro-Oeste | N13: Enviado | O13: Em trânsito
A14: 15 | B14: 2024-09-02 | C14: Sim | D14: Macan GTS | E14: Macan | F14: Combustão | G14: 2024 | H14: 95000 | I14: 3500 | J14: Financiamento | K14: Phoenix | L14: AZ | M14: Oeste | N14: Em trânsito | O14: Em trânsito
A15: 16 | B15: 2024-09-17 | C15: Sim | D15: Taycan Turbo | E15: Taycan | F15: Elétrico | G15: 2023 | H15: 153200.5 | I15: 11 | J15: ACH | K15: Dallas | L15: TX | M15: Sul | N15: Entregue | O15: Entregue
A16: 17 | C16: Não | D16: 911 GT3 | E16: 911 | F16: Combustão | G16: 2024 | H16: 241000 | I16: 750 | J16: Transferência (wire) | K16: Las Vegas | L16: NV | M16: Oeste | N16: Pendente | O16: Pendente
A17: 18 | B17: 2024-05-11 | C17: Sim | D17: Panamera Turbo S | E17: Panamera | F17: Combustão | G17: 2022 | H17: 132000 | I17: 19250 | J17: Dinheiro | K17: San Jose | L17: CA | M17: Oeste | N17: Entregue | O17: Entregue
A18: 19 | B18: 2024-12-12 | C18: Sim | D18: Cayenne Turbo GT | E18: Cayenne | F18: Combustão | G18: 2024 | H18: 188000 | I18: 2100 | J18: Cripto | K18: Houston | L18: TX | M18: Sul | N18: Aguardando entrega | O18: Aguardando
A19: 20 | B19: 2024-12-25 | C19: Sim | D19: 911 Carrera Cabriolet | E19: 911 | F19: Combustão | G19: 2023 | H19: 127800 | I19: 12000 | J19: Cartão de crédito | K19: Atlanta | L19: GA | M19: Sul | N19: Entregue | O19: Entregue
A20: 21 | B20: 2025-01-06 | C20: Sim | D20: Macan | E20: Macan | F20: Combustão | G20: 2021 | H20: 58900 | I20: 33700 | J20: Transferência bancária | K20: Orlando | L20: FL | M20: Sul | N20: Pendente | O20: Pendente
A21: 22 | C21: Não | D21: 718 Spyder RS | E21: 718 | F21: Combustão | G21: 2024 | H21: 164000 | I21: 900 | J21: Financiamento | K21: Portland | L21: OR | M21: Oeste | N21: Em trânsito | O21: Em trânsito
A22: 23 | B22: 2025-02-14 | C22: Sim | D22: Taycan Cross Turismo | E22: Taycan | F22: Elétrico | G22: 2023 | H22: 118500 | I22: 7800 | J22: Transferência (wire) | K22: Charlotte | L22: NC | M22: Sul | N22: Entregue | O22: Entregue
A23: 24 | C23: Não | D23: Cayenne S | E23: Cayenne | F23: Combustão | G23: 2022 | H23: 91300 | I23: 16000 | J23: Cartão de crédito | K23: Nashville | L23: TN | M23: Sul | N23: Pendente | O23: Pendente
A24: 25 | B24: 2025-03-21 | C24: Sim | D24: 911 Targa 4S | E24: 911 | F24: Combustão | G24: 2024 | H24: 158750 | I24: 2500 | J24: Locação (leasing) | K24: Minneapolis | L24: MN | M24: Centro-Oeste | N24: Entregue | O24: Entregue
A25: 26 | B25: 2025-03-28 | C25: Sim | D25: Panamera | E25: Panamera | F25: Combustão | G25: 2020 | H25: 72000 | I25: 49000 | J25: Transferência bancária | K25: Philadelphia | L25: PA | M25: Nordeste | N25: Cancelado | O25: Cancelado
A26: 27 | B26: 2025-04-09 | C26: Sim | D26: Macan Electric | E26: Macan | F26: Elétrico | G26: 2025 | H26: 86500 | I26: 0 | J26: Transferência (wire) | K26: San Antonio | L26: TX | M26: Sul | N26: Entregue | O26: Entregue
A27: 28 | C27: Não | D27: 911 Dakar | E27: 911 | F27: Combustão | G27: 2024 | H27: 270000 | I27: 1050 | J27: Dinheiro | K27: Salt Lake City | L27: UT | M27: Oeste | N27: Aguardando retirada | O27: Aguardando
A28: 29 | B28: 2025-05-12 | C28: Sim | D28: Taycan GTS | E28: Taycan | F28: Elétrico | G28: 2023 | H28: 139000 | I28: 6250 | J28: Financiamento | K28: Raleigh | L28: NC | M28: Sul | N28: Em trânsito | O28: Em trânsito
A29: 30 | B29: 2025-06-18 | C29: Sim | D29: Cayenne | E29: Cayenne | F29: Combustão | G29: 2021 | H29: 76800 | I29: 38400 | J29: Cartão de crédito | K29: Detroit | L29: MI | M29: Centro-Oeste | N29: Entregue | O29: Entregue
A30: 31 | C30: Não | D30: 718 Cayman GT4 RS | E30: 718 | F30: Combustão | G30: 2024 | H30: 173600 | I30: 400 | J30: Transferência (wire) | K30: Columbus | L30: OH | M30: Centro-Oeste | N30: Pendente | O30: Pendente
A31: 32 | B31: 2025-07-07 | C31: Sim | D31: 911 Carrera GTS | E31: 911 | F31: Combustão | G31: 2022 | H31: 119900 | I31: 13600 | J31: Dinheiro | K31: Indianapolis | L31: IN | M31: Centro-Oeste | N31: Entregue | O31: Entregue
A32: 33 | B32: 2025-07-22 | C32: Sim | D32: Panamera 4 E-Hybrid | E32: Panamera | F32: Híbrido | G32: 2023 | H32: 109250 | I32: 8900 | J32: Locação (leasing) | K32: Fort Worth | L32: TX | M32: Sul | N32: Em trânsito | O32: Em trânsito
A33: 34 | B33: 2025-08-14 | C33: Sim | D33: Macan T | E33: Macan | F33: Combustão | G33: 2022 | H33: 82000 | I33: 21750 | J33: Transferência (wire) | K33: Jacksonville | L33: FL | M33: Sul | N33: Entregue | O33: Entregue
A34: 35 | B34: 2025-09-01 | C34: Sim | D34: Taycan Turbo S | E34: Taycan | F34: Elétrico | G34: 2025 | H34: 214000 | I34: 0 | J34: Cripto | K34: San Diego | L34: CA | M34: Oeste | N34: Em análise | O34: Pendente
A35: 36 | C35: Não | D35: 911 Carrera | E35: 911 | F35: Combustão | G35: 2024 | H35: 124500 | I35: 4800 | J35: Cartão de crédito | K35: Tampa | L35: FL | M35: Sul | N35: Entregue | O35: Entregue
A36: 37 | B36: 2025-09-18 | C36: Sim | D36: Cayenne S | E36: Cayenne | F36: Combustão | G36: 2023 | H36: 98200 | I36: 12200 | J36: Transferência bancária | K36: Sacramento | L36: CA | M36: Oeste | N36: Pendente | O36: Pendente
A37: 38 | B37: 2025-10-04 | C37: Sim | D37: Macan | E37: Macan | F37: Combustão | G37: 2022 | H37: 67500 | I37: 24100 | J37: Financiamento | K37: Cleveland | L37: OH | M37: Centro-Oeste | N37: Entregue | O37: Entregue
A38: 39 | B38: 2025-10-12 | C38: Sim | D38: Taycan | E38: Taycan | F38: Elétrico | G38: 2025 | H38: 116900 | I38: 0 | J38: Transferência (wire) | K38: Milwaukee | L38: WI | M38: Centro-Oeste | N38: Em trânsito | O38: Em trânsito
A39: 40 | B39: 2025-10-29 | C39: Sim | D39: Panamera 4S | E39: Panamera | F39: Combustão | G39: 2024 | H39: 112000 | I39: 10 | J39: Dinheiro | K39: Kansas City | L39: MO | M39: Centro-Oeste | N39: Entregue | O39: Entregue
A40: 41 | B40: 2025-02-11 | C40: Sim | D40: 718 Boxster | E40: 718 | F40: Combustão | G40: 2021 | H40: 74000 | I40: 31000 | J40: Cartão de débito | K40: Omaha | L40: NE | M40: Centro-Oeste | N40: Cancelado | O40: Cancelado
A41: 42 | B41: 2025-11-16 | C41: Sim | D41: 911 Turbo | E41: 911 | F41: Combustão | G41: 2024 | H41: 198300 | I41: 2400 | J41: Transferência (wire) | K41: Albuquerque | L41: NM | M41: Oeste | N41: Aguardando entrega | O41: Aguardando
A42: 43 | C42: Não | D42: Cayenne Coupe | E42: Cayenne | F42: Combustão | G42: 2023 | H42: 103750 | I42: 6773 | J42: Transferência (wire) | K42: Tucson | L42: AZ | M42: Oeste | N42: Aguardando aprovação | O42: Pendente
A43: 44 | C43: Não | D43: Macan GTS | E43: Macan | F43: Combustão | G43: 2024 | H43: 93600 | I43: 5800 | J43: Financiamento | K43: Fresno | L43: CA | M43: Oeste | N43: Enviado | O43: Em trânsito
A44: 45 | B44: 2025-12-07 | C44: Sim | D44: Taycan 4S | E44: Taycan | F44: Elétrico | G44: 2025 | H44: 129000 | I44: 0 | J44: ACH | K44: Virginia Beach | L44: VA | M44: Sul | N44: Em trânsito | O44: Em trânsito
A45: 46 | B45: 2025-12-22 | C45: Sim | D45: Panamera Turbo | E45: Panamera | F45: Combustão | G45: 2022 | H45: 136000 | I45: 18400 | J45: Cartão de crédito | K45: Colorado Springs | L45: CO | M45: Oeste | N45: Entregue | O45: Entregue
A46: 47 | C46: Não | D46: 911 GT3 RS | E46: 911 | F46: Combustão | G46: 2024 | H46: 286500 | I46: 700 | J46: Transferência (wire) | K46: Arlington | L46: TX | M46: Sul | N46: Pendente | O46: Pendente
A47: 48 | B47: 2026-01-08 | C47: Sim | D47: Cayenne E-Hybrid | E47: Cayenne | F47: Híbrido | G47: 2023 | H47: 92800 | I47: 15000 | J47: Locação (leasing) | K47: Bakersfield | L47: CA | M47: Oeste | N47: Entregue | O47: Entregue
A48: 49 | B48: 2026-01-15 | C48: Sim | D48: Macan T | E48: Macan | F48: Combustão | G48: 2022 | H48: 72400 | I48: 19750 | J48: Dinheiro | K48: Mesa | L48: AZ | M48: Oeste | N48: Aguardando retirada | O48: Aguardando
A49: 50 | B49: 2026-01-28 | C49: Sim | D49: Taycan Turbo | E49: Taycan | F49: Elétrico | G49: 2025 | H49: 158500 | I49: 3200 | J49: Cripto | K49: Atlanta | L49: GA | M49: Sul | N49: Entregue | O49: Entregue
A50: 51 | B50: 2026-02-03 | C50: Sim | D50: 718 Cayman | E50: 718 | F50: Combustão | G50: 2021 | H50: 69900 | I50: 27600 | J50: Transferência bancária | K50: Long Beach | L50: CA | M50: Oeste | N50: Pendente | O50: Pendente
A51: 52 | C51: Não | D51: 911 Targa 4 | E51: 911 | F51: Combustão | G51: 2024 | H51: 141250 | I51: 2100 | J51: Financiamento | K51: Oakland | L51: CA | M51: Oeste | N51: Em trânsito | O51: Em trânsito
A52: 53 | B52: 2026-02-19 | C52: Sim | D52: Panamera | E52: Panamera | F52: Combustão | G52: 2020 | H52: 71500 | I52: 52000 | J52: Transferência (wire) | K52: Tulsa | L52: OK | M52: Sul | N52: Entregue | O52: Entregue
A53: 54 | B53: 2026-02-25 | C53: Sim | D53: Cayenne Turbo | E53: Cayenne | F53: Combustão | G53: 2023 | H53: 146800 | I53: 11300 | J53: Cartão de crédito | K53: Wichita | L53: KS | M53: Centro-Oeste | N53: Pendente | O53: Pendente
A54: 55 | B54: 2026-03-01 | C54: Sim | D54: Macan Electric | E54: Macan | F54: Elétrico | G54: 2025 | H54: 89700 | I54: 0 | J54: Locação (leasing) | K54: New Orleans | L54: LA | M54: Sul | N54: Entregue | O54: Entregue
A55: 56 | B55: 2026-03-14 | C55: Sim | D55: 911 Carrera S | E55: 911 | F55: Combustão | G55: 2022 | H55: 104600 | I55: 15900 | J55: Transferência bancária | K55: Honolulu | L55: HI | M55: Oeste | N55: Cancelado | O55: Cancelado
A56: 57 | C56: Não | D56: Taycan GTS | E56: Taycan | F56: Elétrico | G56: 2024 | H56: 142000 | I56: 6600 | J56: Transferência (wire) | K56: Anaheim | L56: CA | M56: Oeste | N56: Entregue | O56: Entregue
A57: 58 | B57: 2026-04-08 | C57: Sim | D57: Cayenne | E57: Cayenne | F57: Combustão | G57: 2021 | H57: 78400 | I57: 40250 | J57: Dinheiro | K57: Henderson | L57: NV | M57: Oeste | N57: Aguardando análise | O57: Aguardando
A58: 59 | C58: Não | D58: 718 Spyder RS | E58: 718 | F58: Combustão | G58: 2025 | H58: 169000 | I58: 850 | J58: Financiamento | K58: Lexington | L58: KY | M58: Sul | N58: Em trânsito | O58: Em trânsito
A59: 60 | B59: 2026-04-21 | C59: Sim | D59: 911 Dakar | E59: 911 | F59: Combustão | G59: 2024 | H59: 268900 | I59: 1400 | J59: Cartão de crédito | K59: Riverside | L59: CA | M59: Oeste | N59: Entregue | O59: Entregue
A60: 61 | B60: 2026-04-29 | C60: Sim | D60: Panamera 4 | E60: Panamera | F60: Combustão | G60: 2023 | H60: 101300 | I60: 12700 | J60: Transferência (wire) | K60: Corpus Christi | L60: TX | M60: Sul | N60: Pendente | O60: Pendente
A61: 62 | B61: 2026-05-05 | C61: Sim | D61: Macan S | E61: Macan | F61: Combustão | G61: 2021 | H61: 66750 | I61: 29800 | J61: Dinheiro | K61: St. Louis | L61: MO | M61: Centro-Oeste | N61: Entregue | O61: Entregue
A62: 63 | B62: 2026-05-14 | C62: Sim | D62: Taycan Cross Turismo | E62: Taycan | F62: Elétrico | G62: 2024 | H62: 127900 | I62: 7500 | J62: Locação (leasing) | K62: Pittsburgh | L62: PA | M62: Nordeste | N62: Em trânsito | O62: Em trânsito
A63: 64 | B63: 2026-05-23 | C63: Sim | D63: Cayenne Turbo GT | E63: Cayenne | F63: Combustão | G63: 2025 | H63: 200000 | I63: 1950 | J63: Transferência (wire) | K63: Cincinnati | L63: OH | M63: Centro-Oeste | N63: Entregue | O63: Entregue
A64: 65 | B64: 2026-06-02 | C64: Sim | D64: 911 Carrera Cabriolet | E64: 911 | F64: Combustão | G64: 2023 | H64: 132000 | I64: 8800 | J64: Cripto | K64: Anchorage | L64: AK | M64: Oeste | N64: Em análise | O64: Pendente
A65: 66 | B65: 2026-06-15 | C65: Sim | D65: 718 Cayman GT4 RS | E65: 718 | F65: Combustão | G65: 2024 | H65: 176400 | I65: 600 | J65: Cartão de crédito | K65: Plano | L65: TX | M65: Sul | N65: Entregue | O65: Entregue
A66: 67 | C66: Não | D66: Panamera 4 E-Hybrid | E66: Panamera | F66: Híbrido | G66: 2022 | H66: 108500 | I66: 16200 | J66: Transferência bancária | K66: Newark | L66: NJ | M66: Nordeste | N66: Cancelado | O66: Cancelado
A67: 68 | B67: 2026-07-07 | C67: Sim | D67: Macan | E67: Macan | F67: Combustão | G67: 2021 | H67: 59000 | I67: 36000 | J67: Financiamento | K67: Greensboro | L67: NC | M67: Sul | N67: Aguardando entrega | O67: Aguardando
A68: 69 | B68: 2026-07-20 | C68: Sim | D68: Taycan Turbo S | E68: Taycan | F68: Elétrico | G68: 2025 | H68: 218000 | I68: 0 | J68: Transferência (wire) | K68: Lincoln | L68: NE | M68: Centro-Oeste | N68: Pendente | O68: Pendente
A69: 70 | C69: Não | D69: Cayenne S | E69: Cayenne | F69: Combustão | G69: 2024 | H69: 99950 | I69: 5300 | J69: Cartão de débito | K69: Jersey City | L69: NJ | M69: Nordeste | N69: Entregue | O69: Entregue
A70: 71 | B70: 2026-04-08 | C70: Sim | D70: 911 Carrera GTS | E70: 911 | F70: Combustão | G70: 2024 | H70: 121750 | I70: 5872 | J70: Cartão de crédito | K70: Chandler | L70: AZ | M70: Oeste | N70: Entregue | O70: Entregue
A71: 72 | B71: 2026-08-18 | C71: Sim | D71: 718 Boxster GTS | E71: 718 | F71: Combustão | G71: 2023 | H71: 91500 | I71: 13300 | J71: Locação (leasing) | K71: Reno | L71: NV | M71: Oeste | N71: Enviado | O71: Em trânsito
A72: 73 | B72: 2026-08-31 | C72: Sim | D72: Panamera Turbo S | E72: Panamera | F72: Combustão | G72: 2022 | H72: 134000 | I72: 20100 | J72: Transferência (wire) | K72: Buffalo | L72: NY | M72: Nordeste | N72: Em trânsito | O72: Em trânsito
A73: 74 | B73: 2026-09-09 | C73: Sim | D73: Macan GTS | E73: Macan | F73: Combustão | G73: 2024 | H73: 96800 | I73: 0 | J73: ACH | K73: Durham | L73: NC | M73: Sul | N73: Entregue | O73: Entregue
A74: 75 | B74: 2026-09-17 | C74: Sim | D74: Taycan 4S | E74: Taycan | F74: Elétrico | G74: 2025 | H74: 131600 | I74: 2900 | J74: Transferência (wire) | K74: Laredo | L74: TX | M74: Sul | N74: Aguardando aprovação | O74: Pendente
A75: 76 | B75: 2026-09-28 | C75: Sim | D75: Cayenne E-Hybrid | E75: Cayenne | F75: Híbrido | G75: 2023 | H75: 94300 | I75: 13100 | J75: Dinheiro | K75: Madison | L75: WI | M75: Centro-Oeste | N75: Entregue | O75: Entregue
A76: 77 | B76: 2026-10-06 | C76: Sim | D76: 911 Turbo S | E76: 911 | F76: Combustão | G76: 2025 | H76: 242000 | I76: 1100 | J76: Cripto | K76: Lubbock | L76: TX | M76: Sul | N76: Aguardando retirada | O76: Aguardando
A77: 78 | B77: 2026-10-16 | C77: Sim | D77: 718 Cayman S | E77: 718 | F77: Combustão | G77: 2022 | H77: 82750 | I77: 22500 | J77: Cartão de crédito | K77: Toledo | L77: OH | M77: Centro-Oeste | N77: Cancelado | O77: Cancelado
A78: 79 | B78: 2026-10-29 | C78: Sim | D78: Macan Electric | E78: Macan | F78: Elétrico | G78: 2026 | H78: 91300 | I78: 0 | J78: Transferência (wire) | K78: Irvine | L78: CA | M78: Oeste | N78: Entregue | O78: Entregue
A79: 80 | B79: 2026-11-03 | C79: Sim | D79: Panamera | E79: Panamera | F79: Combustão | G79: 2021 | H79: 79900 | I79: 44800 | J79: Financiamento | K79: Garland | L79: TX | M79: Sul | N79: Pendente | O79: Pendente
A80: 81 | C80: Não | D80: Cayenne Coupe | E80: Cayenne | F80: Combustão | G80: 2024 | H80: 111000 | I80: 6700 | J80: Transferência bancária | K80: Irving | L80: TX | M80: Sul | N80: Em trânsito | O80: Em trânsito
A81: 82 | B81: 2026-12-11 | C81: Sim | D81: 911 Targa 4S | E81: 911 | F81: Combustão | G81: 2023 | H81: 156500 | I81: 4200 | J81: Dinheiro | K81: Chesapeake | L81: VA | M81: Sul | N81: Entregue | O81: Entregue
A82: 83 | B82: 2026-12-24 | C82: Sim | D82: Taycan | E82: Taycan | F82: Elétrico | G82: 2025 | H82: 119900 | I82: 1250 | J82: Locação (leasing) | K82: Scottsdale | L82: AZ | M82: Oeste | N82: Pendente | O82: Pendente
A83: 84 | C83: Não | D83: Macan T | E83: Macan | F83: Combustão | G83: 2022 | H83: 73200 | I83: 18600 | J83: Transferência (wire) | K83: Norfolk | L83: VA | M83: Sul | N83: Entregue | O83: Entregue
A84: 85 | B84: 2026-12-28 | C84: Sim | D84: 911 GT3 | E84: 911 | F84: Combustão | G84: 2024 | H84: 224000 | I84: 3000 | J84: Transferência (wire) | K84: Boise | L84: ID | M84: Oeste | N84: Aguardando entrega | O84: Aguardando
A85: 86 | B85: 2027-01-15 | C85: Sim | D85: 911 Carrera | E85: 911 | F85: Combustão | G85: 2024 | H85: 126900 | I85: 7200 | J85: Cartão de crédito | K85: Orlando | L85: FL | M85: Sul | N85: Entregue | O85: Entregue
A86: 87 | B86: 2027-01-29 | C86: Sim | D86: Cayenne | E86: Cayenne | F86: Combustão | G86: 2023 | H86: 84500 | I86: 21400 | J86: Transferência bancária | K86: San Jose | L86: CA | M86: Oeste | N86: Pendente | O86: Pendente
A87: 88 | B87: 2027-02-11 | C87: Sim | D87: Macan S | E87: Macan | F87: Combustão | G87: 2022 | H87: 69800 | I87: 26300 | J87: Financiamento | K87: Tampa | L87: FL | M87: Sul | N87: Entregue | O87: Entregue
A88: 89 | C88: Não | D88: Taycan 4S | E88: Taycan | F88: Elétrico | G88: 2025 | H88: 132700 | I88: 0 | J88: Transferência (wire) | K88: Denver | L88: CO | M88: Oeste | N88: Em trânsito | O88: Em trânsito
A89: 90 | B89: 2027-03-05 | C89: Sim | D89: Panamera | E89: Panamera | F89: Combustão | G89: 2021 | H89: 81000 | I89: 42 | J89: Dinheiro | K89: Austin | L89: TX | M89: Sul | N89: Entregue | O89: Entregue
A90: 91 | B90: 2027-03-18 | C90: Sim | D90: 718 Cayman | E90: 718 | F90: Combustão | G90: 2023 | H90: 78900 | I90: 17500 | J90: Cartão de débito | K90: Seattle | L90: WA | M90: Oeste | N90: Cancelado | O90: Cancelado
A91: 92 | B91: 2027-04-02 | C91: Sim | D91: 911 Turbo S | E91: 911 | F91: Combustão | G91: 2026 | H91: 249300 | I91: 900 | J91: Transferência (wire) | K91: Boston | L91: MA | M91: Nordeste | N91: Aguardando entrega | O91: Aguardando
A92: 93 | C92: Não | D92: Cayenne Coupe | E92: Cayenne | F92: Combustão | G92: 2024 | H92: 108750 | I92: 5530 | J92: Transferência (wire) | K92: Phoenix | L92: AZ | M92: Oeste | N92: Aguardando aprovação | O92: Pendente
A93: 94 | C93: Não | D93: Macan Electric | E93: Macan | F93: Elétrico | G93: 2026 | H93: 92600 | I93: 0 | J93: Financiamento | K93: Chicago | L93: IL | M93: Centro-Oeste | N93: Enviado | O93: Em trânsito
A94: 95 | B94: 2027-05-12 | C94: Sim | D94: Taycan Turbo | E94: Taycan | F94: Elétrico | G94: 2025 | H94: 164000 | I94: 0 | J94: ACH | K94: Dallas | L94: TX | M94: Sul | N94: Em trânsito | O94: Em trânsito
A95: 96 | B95: 2027-05-27 | C95: Sim | D95: Panamera 4S | E95: Panamera | F95: Combustão | G95: 2024 | H95: 119000 | I95: 13400 | J95: Cartão de crédito | K95: San Francisco | L95: CA | M95: Oeste | N95: Entregue | O95: Entregue
A96: 97 | C96: Não | D96: 911 GT3 | E96: 911 | F96: Combustão | G96: 2026 | H96: 232500 | I96: 1700 | J96: Transferência (wire) | K96: Las Vegas | L96: NV | M96: Oeste | N96: Pendente | O96: Pendente
A97: 98 | B97: 2027-06-18 | C97: Sim | D97: Cayenne E-Hybrid | E97: Cayenne | F97: Híbrido | G97: 2023 | H97: 96800 | I97: 14000 | J97: Locação (leasing) | K97: Charlotte | L97: NC | M97: Sul | N97: Entregue | O97: Entregue
A98: 99 | B98: 2027-07-03 | C98: Sim | D98: Macan T | E98: Macan | F98: Combustão | G98: 2022 | H98: 74400 | I98: 20750 | J98: Dinheiro | K98: Mesa | L98: AZ | M98: Oeste | N98: Aguardando retirada | O98: Aguardando
A99: 100 | B99: 2027-07-22 | C99: Sim | D99: Taycan GTS | E99: Taycan | F99: Elétrico | G99: 2025 | H99: 148500 | I99: 5200 | J99: Cripto | K99: Atlanta | L99: GA | M99: Sul | N99: Entregue | O99: Entregue
A100: 101 | B100: 2027-08-08 | C100: Sim | D100: 718 Boxster | E100: 718 | F100: Combustão | G100: 2021 | H100: 71900 | I100: 29600 | J100: Transferência bancária | K100: Long Beach | L100: CA | M100: Oeste | N100: Pendente | O100: Pendente
A101: 102 | C101: Não | D101: 911 Targa 4 | E101: 911 | F101: Combustão | G101: 2024 | H101: 143250 | I101: 3100 | J101: Financiamento | K101: Oakland | L101: CA | M101: Oeste | N101: Em trânsito | O101: Em trânsito
...

Sheet Dicionário
A1: DICIONÁRIO DE DADOS
A3: Coluna | B3: Tipo | C3: Descrição
A4: id_venda | B4: Número | C4: Identificador da venda (6 a 105).
A5: data_venda | B5: Data | C5: Data da venda; vazio quando a data original era impossível (ex.: 30/02).
A6: data_valida | B6: Sim/Não | C6: Indica se a data pôde ser recuperada da coluna sanitizada.
A7: modelo | B7: Texto | C7: Modelo completo (ex.: 911 Turbo S, Taycan 4S, Cayenne Coupe).
A8: familia | B8: Texto | C8: Primeira palavra do modelo: 718, 911, Cayenne, Macan, Panamera ou Taycan.
A9: combustivel | B9: Texto | C9: Elétrico (Taycan/Macan Electric), Híbrido (E-Hybrid) ou Combustão.
A10: ano_modelo | B10: Número | C10: Ano-modelo do veículo (2020 a 2026), convertido de texto.
A11: preco_usd | B11: Moeda | C11: Preço de venda em dólares (base original), convertido de texto.
A12: quilometragem_mi | B12: Número | C12: Quilometragem em milhas, convertida de texto.
A13: metodo_pagamento | B13: Texto | C13: Forma de pagamento padronizada e traduzida.
A14: cidade | B14: Texto | C14: Cidade da venda (EUA).
... A18: status_grupo | B18: Texto | C18: Grupo do status: Entregue / Em trânsito / Pendente / Aguardando / Cancelado.
A20: Privacidade
A21: As colunas customer_name e salesperson da planilha original foram REMOVIDAS: a base tratada vai embutida na dashboard pública. Nenhum nome de pessoa permanece.

Sheet Tratamento
A1: REGISTRO DO TRATAMENTO (do dado bruto ao dado tratado)
A3: # | B3: Etapa | C3: O que foi feito | D3: Resultado
A4: 1 | B4: Origem | C4: Planilha oficial do desafio (hermes.dio.me), aba Sanitized. | D4: 100 registros, 21 colunas (cruas + sanitizadas)
A5: 2 | B5: Colunas cruas | C5: Descartadas as 10 versões cruas (sale_date, porsche_model, model_year, sale_price, vehicle_mileage, payment_method, city, state, delivery_status e sale_id foi mantido). | D5: só as colunas "Sanitized" permanecem
A6: 3 | B6: Tipos | C6: preco_usd, ano_modelo e quilometragem_mi convertidos de texto para número; datas ISO para data. | D6: números somam e ordenam; datas comparáveis
A7: 4 | B7: Datas | C7: 24 datas sanitizadas = INVALID (datas impossíveis, ex.: 30/02). Campo data_venda fica vazio e data_valida = Não. | D7: 76 datas válidas; 24 marcadas com transparência
A8: 5 | B8: Privacidade | C8: Removidas customer_name e salesperson antes de publicar. | D8: 0 nomes de pessoas na base tratada e na dashboard
A9: 6 | B9: Derivadas | C9: familia (1ª palavra), combustivel (Elétrico/Híbrido/Combustão), regiao (Censo EUA) e status_grupo (agrupamento dos 10 status em 5). | D9: 4 colunas novas para os filtros
A10: 7 | B10: Validação | C10: 100 IDs únicos; preço mínimo US$ 58.900 e máximo US$ 286.500; anos de 2020 a 2026; soma da receita confere com a dashboard. | D10: base confiável para análise
A12: SHA-256 da planilha original: f874650657ca4e1a99fd4462b297bfc5fd9915e8e693956d9cec47eda2cb2e2d

Sheet Perguntas
A1: PERGUNTAS DE NEGÓCIO E ONDE ESTÃO AS RESPOSTAS
A3: # | B3: Pergunta | C3: Visual na dashboard | D3: Por quê
A4: 1 | B4: Quais modelos da Porsche geram mais receita? | C4: Barras horizontais (Top 10 modelos) | D4: Identifica os campeões de receita por unidade vendida.
A5: 2 | B5: Como a receita se distribui por ano-modelo? | C5: Colunas por ano (2020–2026) | D5: Mostra a evolução do mix e a força dos anos recentes.
A6: 3 | B6: Como os clientes pagam? | C6: Rosca por método de pagamento | D6: Orienta política de financiamento, leasing e meios digitais.
A7: 4 | B7: Quais estados concentram as vendas? | C7: Barras por estado (Top 10) + UFs | D7: Aponta onde reforçar concessionárias e campanhas.
A8: 5 | B8: Como está a situação das entregas? | C8: Barras por grupo de status | D8: Mede eficiência logística (entregues × pendências × cancelamentos).

Sheet Resumo
A1: RESUMO PARA CONFERÊNCIA (fórmulas sobre a aba Base Tratada)
A3: A aba existe para conferir os números da dashboard com fórmulas do Excel.
A5: 1) POR FAMÍLIA
A6: Família | B6: Vendas | C6: Receita (US$) | D6: Ticket médio (US$)
A7: 718 | B7: =COUNTIF('Base Tratada'!$E$5:$E$104,A7) | C7: =SUMIF('Base Tratada'!$E$5:$E$104,A7,'Base Tratada'!$H$5:$H$104) | D7: =IF(B7=0,0,C7/B7)
A8: 911 | B8: =COUNTIF('Base Tratada'!$E$5:$E$104,A8) | C8: =SUMIF('Base Tratada'!$E$5:$E$104,A8,'Base Tratada'!$H$5:$H$104) | D8: =IF(B8=0,0,C8/B8)
A9: Cayenne | B9: =COUNTIF('Base Tratada'!$E$5:$E$104,A9) | C9: =SUMIF('Base Tratada'!$E$5:$E$104,A9,'Base Tratada'!$H$5:$H$104) | D9: =IF(B9=0,0,C9/B9)
A10: Macan | B10: =COUNTIF('Base Tratada'!$E$5:$E$104,A10) | C10: =SUMIF('Base Tratada'!$E$5:$E$104,A10,'Base Tratada'!$H$5:$H$104) | D10: =IF(B10=0,0,C10/B10)
A11: Panamera | B11: =COUNTIF('Base Tratada'!$E$5:$E$104,A11) | C11: =SUMIF('Base Tratada'!$E$5:$E$104,A11,'Base Tratada'!$H$5:$H$104) | D11: =IF(B11=0,0,C11/B11)
A12: Taycan | B12: =COUNTIF('Base Tratada'!$E$5:$E$104,A12) | C12: =SUMIF('Base Tratada'!$E$5:$E$104,A12,'Base Tratada'!$H$5:$H$104) | D12: =IF(B12=0,0,C12/B12)
A14: 2) POR ANO-MODELO
A15: Ano | B15: Vendas | C15: Receita (US$) | D15: Ticket médio (US$)
A16: 2020 | B16: =COUNTIF('Base Tratada'!$G$5:$G$104,A16) | C16: =SUMIF('Base Tratada'!$G$5:$G$104,A16,'Base Tratada'!$H$5:$H$104) | D16: =IF(B16=0,0,C16/B16)
A17: 2021 | B17: =COUNTIF('Base Tratada'!$G$5:$G$104,A17) | C17: =SUMIF('Base Tratada'!$G$5:$G$104,A17,'Base Tratada'!$H$5:$H$104) | D17: =IF(B17=0,0,C17/B17)
A18: 2022 | B18: =COUNTIF('Base Tratada'!$G$5:$G$104,A18) | C18: =SUMIF('Base Tratada'!$G$5:$G$104,A18,'Base Tratada'!$H$5:$H$104) | D18: =IF(B18=0,0,C18/B18)
A19: 2023 | B19: =COUNTIF('Base Tratada'!$G$5:$G$104,A19) | C19: =SUMIF('Base Tratada'!$G$5:$G$104,A19,'Base Tratada'!$H$5:$H$104) | D19: =IF(B19=0,0,C19/B19)
A20: 2024 | B20: =COUNTIF('Base Tratada'!$G$5:$G$104,A20) | C20: =SUMIF('Base Tratada'!$G$5:$G$104,A20,'Base Tratada'!$H$5:$H$104) | D20: =IF(B20=0,0,C20/B20)
A21: 2025 | B21: =COUNTIF('Base Tratada'!$G$5:$G$104,A21) | C21: =SUMIF('Base Tratada'!$G$5:$G$104,A21,'Base Tratada'!$H$5:$H$104) | D21: =IF(B21=0,0,C21/B21)
A22: 2026 | B22: =COUNTIF('Base Tratada'!$G$5:$G$104,A22) | C22: =SUMIF('Base Tratada'!$G$5:$G$104,A22,'Base Tratada'!$H$5:$H$104) | D22: =IF(B22=0,0,C22/B22)
A24: 3) POR MÉTODO DE PAGAMENTO
A25: Pagamento | B25: Vendas | C25: Receita (US$) | D25: Ticket médio (US$)
A26: Transferência (wire) | B26: =COUNTIF('Base Tratada'!$J$5:$J$104,A26) | C26: =SUMIF('Base Tratada'!$J$5:$J$104,A26,'Base Tratada'!$H$5:$H$104) | D26: =IF(B26=0,0,C26/B26)
A27: Cartão de crédito | B27: =COUNTIF('Base Tratada'!$J$5:$J$104,A27) | C27: =SUMIF('Base Tratada'!$J$5:$J$104,A27,'Base Tratada'!$H$5:$H$104) | D27: =IF(B27=0,0,C27/B27)
A28: Financiamento | B28: =COUNTIF('Base Tratada'!$J$5:$J$104,A28) | C28: =SUMIF('Base Tratada'!$J$5:$J$104,A28,'Base Tratada'!$H$5:$H$104) | D28: =IF(B28=0,0,C28/B28)
A29: Dinheiro | B29: =COUNTIF('Base Tratada'!$J$5:$J$104,A29) | C29: =SUMIF('Base Tratada'!$J$5:$J$104,A29,'Base Tratada'!$H$5:$H$104) | D29: =IF(B29=0,0,C29/B29)
A30: Transferência bancária | B30: =COUNTIF('Base Tratada'!$J$5:$J$104,A30) | C30: =SUMIF('Base Tratada'!$J$5:$J$104,A30,'Base Tratada'!$H$5:$H$104) | D30: =IF(B30=0,0,C30/B30)
A31: Locação (leasing) | B31: =COUNTIF('Base Tratada'!$J$5:$J$104,A31) | C31: =SUMIF('Base Tratada'!$J$5:$J$104,A31,'Base Tratada'!$H$5:$H$104) | D31: =IF(B31=0,0,C31/B31)
A32: Cripto | B32: =COUNTIF('Base Tratada'!$J$5:$J$104,A32) | C32: =SUMIF('Base Tratada'!$J$5:$J$104,A32,'Base Tratada'!$H$5:$H$104) | D32: =IF(B32=0,0,C32/B32)
A33: Cartão de débito | B33: =COUNTIF('Base Tratada'!$J$5:$J$104,A33) | C33: =SUMIF('Base Tratada'!$J$5:$J$104,A33,'Base Tratada'!$H$5:$H$104) | D33: =IF(B33=0,0,C33/B33)
A34: ACH | B34: =COUNTIF('Base Tratada'!$J$5:$J$104,A34) | C34: =SUMIF('Base Tratada'!$J$5:$J$104,A34,'Base Tratada'!$H$5:$H$104) | D34: =IF(B34=0,0,C34/B34)
A36: 4) POR GRUPO DE STATUS
A37: Status | B37: Vendas | C37: Receita (US$) | D37: Ticket médio (US$)
A38: Entregue | B38: =COUNTIF('Base Tratada'!$O$5:$O$104,A38) | C38: =SUMIF('Base Tratada'!$O$5:$O$104,A38,'Base Tratada'!$H$5:$H$104) | D38: =IF(B38=0,0,C38/B38)
A39: Pendente | B39: =COUNTIF('Base Tratada'!$O$5:$O$104,A39) | C39: =SUMIF('Base Tratada'!$O$5:$O$104,A39,'Base Tratada'!$H$5:$H$104) | D39: =IF(B39=0,0,C39/B39)
A40: Em trânsito | B40: =COUNTIF('Base Tratada'!$O$5:$O$104,A40) | C40: =SUMIF('Base Tratada'!$O$5:$O$104,A40,'Base Tratada'!$H$5:$H$104) | D40: =IF(B40=0,0,C40/B40)
A41: Aguardando | B41: =COUNTIF('Base Tratada'!$O$5:$O$104,A41) | C41: =SUMIF('Base Tratada'!$O$5:$O$104,A41,'Base Tratada'!$H$5:$H$104) | D41: =IF(B41=0,0,C41/B41)
A42: Cancelado | B42: =COUNTIF('Base Tratada'!$O$5:$O$104,A42) | C42: =SUMIF('Base Tratada'!$O$5:$O$104,A42,'Base Tratada'!$H$5:$H$104) | D42: =IF(B42=0,0,C42/B42)
A44: 5) CONFERÊNCIA
A45: Registros na base | C45: =COUNTA('Base Tratada'!A5:A104)
A46: Receita total (US$) | C46: =SUM('Base Tratada'!H5:H104)
A47: Ticket médio (US$) | C47: =AVERAGE('Base Tratada'!H5:H104)
A48: Datas válidas | C48: =COUNTIF('Base Tratada'!C5:C104,"Sim")
A49: Datas inválidas (marcadas) | C49: =COUNTIF('Base Tratada'!C5:C104,"Não")
